billiez/__init__.py
billiez-0.2.2.dist-info/LICENSE.txt
billiez-0.2.2.dist-info/METADATA
billiez-0.2.2.dist-info/WHEEL
billiez-0.2.2.dist-info/top_level.txt
billiez-0.2.2.dist-info/RECORD
