Metadata-Version: 2.1
Name: billiez
Version: 0.2.2
Summary: NVIDIA API wrapper for AI text generation
Author: billiez
Classifier: Programming Language :: Python :: 3
Classifier: License :: OSI Approved :: MIT License
Classifier: Operating System :: OS Independent
Requires-Python: >=3.6
License-File: LICENSE.txt
Requires-Dist: openai>=1.0
